pyxjustiz-1.1.0.dist-info/licenses/LICENSE
xjustiz/__init__.py
xjustiz/__main__.py
xjustiz/model_gen/__init__.py
xjustiz/model_gen/xjustiz_0000_grunddatensatz_3_6.py
xjustiz/model_gen/xjustiz_0005_nachrichten_3_2.py
xjustiz/model_gen/xjustiz_0010_cl_allgemein_3_7.py
xjustiz/model_gen/xjustiz_0020_cl_gerichte_3_3.py
xjustiz/model_gen/xjustiz_0030_cl_rechtsform_3_3.py
xjustiz/model_gen/xjustiz_0040_cl_rollenbezeichnung_3_5.py
xjustiz/model_gen/xjustiz_0050_cl_staaten_3_2.py
xjustiz/model_gen/xjustiz_0060_cl_telekommunikation_3_1.py
xjustiz/model_gen/xjustiz_0070_cl_justizvollzugsanstalt_3_1.py
xjustiz/model_gen/xjustiz_0080_cl_register_3_3.py
xjustiz/model_gen/xjustiz_0095_cl_personalstatut_3_0.py
xjustiz/model_gen/xjustiz_0200_familie_3_1.py
xjustiz/model_gen/xjustiz_0210_cl_familie_3_0.py
xjustiz/model_gen/xjustiz_0240_cl_versorgungsauskunft_3_0.py
xjustiz/model_gen/xjustiz_0250_versorgungsauskunft_3_3.py
xjustiz/model_gen/xjustiz_0300_insolvenz_3_5.py
xjustiz/model_gen/xjustiz_0320_cl_insolvenz_3_1.py
xjustiz/model_gen/xjustiz_0330_cl_nachrichten_3_1.py
xjustiz/model_gen/xjustiz_0340_cl_iri_3_0.py
xjustiz/model_gen/xjustiz_0400_register_3_4.py
xjustiz/model_gen/xjustiz_0410_cl_register_3_1.py
xjustiz/model_gen/xjustiz_0420_cl_vertretung_register_3_0.py
xjustiz/model_gen/xjustiz_0500_straf_3_6.py
xjustiz/model_gen/xjustiz_0510_cl_straf_3_5.py
xjustiz/model_gen/xjustiz_0520_cl_personenwerte_3_2.py
xjustiz/model_gen/xjustiz_0530_cl_instanzwerte_3_1.py
xjustiz/model_gen/xjustiz_0540_cl_kfzkennzeichen_3_1.py
xjustiz/model_gen/xjustiz_0550_cl_nachrichten_3_3.py
xjustiz/model_gen/xjustiz_0600_mahn_3_4.py
xjustiz/model_gen/xjustiz_0610_cl_mahn_3_0.py
xjustiz/model_gen/xjustiz_0900_vollstreckung_3_3.py
xjustiz/model_gen/xjustiz_0910_cl_vollstreckung_3_1.py
xjustiz/model_gen/xjustiz_1000_vorsorgeregister_3_1.py
xjustiz/model_gen/xjustiz_1010_cl_vorsorgeregister_3_0.py
xjustiz/model_gen/xjustiz_1300_aussonderung_3_2.py
xjustiz/model_gen/xjustiz_1310_cl_aussonderung_3_0.py
pyxjustiz-1.1.0.dist-info/METADATA
pyxjustiz-1.1.0.dist-info/WHEEL
pyxjustiz-1.1.0.dist-info/top_level.txt
pyxjustiz-1.1.0.dist-info/RECORD
