Metadata-Version: 2.4
Name: pyxjustiz
Version: 1.1.0
Summary: Python XJustiz XML models from official XSDs with easy parsing, serialization, and validation.
Author-email: nbdy <me@nbdy.io>
License: This is free and unencumbered software released into the public domain.
Project-URL: Homepage, https://github.com/nbdy/pyxjustiz
Project-URL: Documentation, https://github.com/nbdy/pyxjustiz
Project-URL: Source, https://github.com/nbdy/pyxjustiz
Project-URL: Issues, https://github.com/nbdy/pyxjustiz/issues
Keywords: xjustiz,xml,schemas,xsdata,pydantic
Classifier: Development Status :: 3 - Alpha
Classifier: Intended Audience :: Developers
Classifier: License :: OSI Approved :: MIT License
Classifier: Programming Language :: Python
Classifier: Programming Language :: Python :: 3
Classifier: Programming Language :: Python :: 3 :: Only
Classifier: Programming Language :: Python :: 3.10
Classifier: Programming Language :: Python :: 3.11
Classifier: Programming Language :: Python :: 3.12
Classifier: Programming Language :: Python :: 3.13
Classifier: Programming Language :: Python :: 3.14
Classifier: Typing :: Typed
Requires-Python: >=3.10
License-File: LICENSE
Requires-Dist: xsdata[cli]>=26.1
Dynamic: license-file
